{
  "polygons": [
    {
      "polygonCoordinates": [
        [
          92.68344465590891,
          30.15340296171783
        ],
        [
          90.79353685720154,
          26.677562504545485
        ],
        [
          98.83663283774672,
          25.533807254871693
        ],
        [
          100.02331912995831,
          28.853765371491217
        ]
      ],
      "selectedStations": [
        {
          "lon": 99.254,
          "lat": 28.844,
          "ve": 12.3,
          "vn": -10.7,
          "ve_err": 0.1,
          "vn_err": 0.1,
          "name": "H188"
        },
        {
          "lon": 99.757,
          "lat": 28.32,
          "ve": 10.3,
          "vn": -12.4,
          "ve_err": 0.1,
          "vn_err": 0.1,
          "name": "H190"
        },
        {
          "lon": 98.914,
          "lat": 28.442,
          "ve": 11.1,
          "vn": -10.2,
          "ve_err": 0.1,
          "vn_err": 0.1,
          "name": "H191"
        },
        {
          "lon": 99.027,
          "lat": 27.611,
          "ve": 6.9,
          "vn": -10.5,
          "ve_err": 0.1,
          "vn_err": 0.1,
          "name": "H193"
        },
        {
          "lon": 98.668,
          "lat": 27.759,
          "ve": 7.7,
          "vn": -9,
          "ve_err": 0.1,
          "vn_err": 0.1,
          "name": "H194"
        },
        {
          "lon": 99.293,
          "lat": 27.18,
          "ve": 4.6,
          "vn": -11.1,
          "ve_err": 0.2,
          "vn_err": 0.2,
          "name": "H196"
        },
        {
          "lon": 98.878,
          "lat": 26.909,
          "ve": 3.3,
          "vn": -9.7,
          "ve_err": 0.1,
          "vn_err": 0.1,
          "name": "H197"
        },
        {
          "lon": 98.923,
          "lat": 26.548,
          "ve": 1,
          "vn": -9.7,
          "ve_err": 0.1,
          "vn_err": 0.1,
          "name": "H200"
        },
        {
          "lon": 98.815,
          "lat": 25.987,
          "ve": 1.4,
          "vn": -8.6,
          "ve_err": 0.1,
          "vn_err": 0.1,
          "name": "H203"
        },
        {
          "lon": 98.873,
          "lat": 27.297,
          "ve": 5.2,
          "vn": -9.3,
          "ve_err": 0.2,
          "vn_err": 0.1,
          "name": "H314"
        },
        {
          "lon": 99.339,
          "lat": 28.218,
          "ve": 12.1,
          "vn": -11.1,
          "ve_err": 0.2,
          "vn_err": 0.1,
          "name": "H318"
        },
        {
          "lon": 99.433,
          "lat": 27.764,
          "ve": 8.3,
          "vn": -11.4,
          "ve_err": 0.1,
          "vn_err": 0.1,
          "name": "H319"
        },
        {
          "lon": 96.868,
          "lat": 29.391,
          "ve": 15.5,
          "vn": -3,
          "ve_err": 0.1,
          "vn_err": 0.1,
          "name": "J013"
        },
        {
          "lon": 93.146,
          "lat": 29.94,
          "ve": 22.1,
          "vn": 14.1,
          "ve_err": 0.4,
          "vn_err": 0.4,
          "name": "J022"
        },
        {
          "lon": 92.399,
          "lat": 28.422,
          "ve": 16.7,
          "vn": 16.7,
          "ve_err": 0.1,
          "vn_err": 0.1,
          "name": "J032"
        },
        {
          "lon": 91.91,
          "lat": 27.971,
          "ve": 14.6,
          "vn": 20.1,
          "ve_err": 0.1,
          "vn_err": 0.1,
          "name": "J034"
        },
        {
          "lon": 93.073,
          "lat": 29.044,
          "ve": 18.4,
          "vn": 13.2,
          "ve_err": 0.1,
          "vn_err": 0.1,
          "name": "J375"
        },
        {
          "lon": 97.054,
          "lat": 28.451,
          "ve": 13.6,
          "vn": 1,
          "ve_err": 0.1,
          "vn_err": 0.1,
          "name": "J394"
        },
        {
          "lon": 97.181,
          "lat": 29.282,
          "ve": 14.8,
          "vn": -3.6,
          "ve_err": 0.1,
          "vn_err": 0.1,
          "name": "J395"
        },
        {
          "lon": 97.469,
          "lat": 28.72,
          "ve": 12.3,
          "vn": -5.4,
          "ve_err": 0.2,
          "vn_err": 0.3,
          "name": "J398"
        },
        {
          "lon": 97.403,
          "lat": 28.992,
          "ve": 13.2,
          "vn": -4.1,
          "ve_err": 0.2,
          "vn_err": 0.2,
          "name": "J422"
        },
        {
          "lon": 97.466,
          "lat": 28.661,
          "ve": 12.8,
          "vn": -4.6,
          "ve_err": 0.2,
          "vn_err": 0.2,
          "name": "XZCY"
        },
        {
          "lon": 94.108,
          "lat": 28.257,
          "ve": 17,
          "vn": 16.8,
          "ve_err": 3.2,
          "vn_err": 3.5,
          "name": "13KM"
        },
        {
          "lon": 94.047,
          "lat": 28.325,
          "ve": 19.8,
          "vn": 16.2,
          "ve_err": 2.7,
          "vn_err": 3.3,
          "name": "35KM"
        },
        {
          "lon": 94.728,
          "lat": 29.684,
          "ve": 15,
          "vn": 6.1,
          "ve_err": 3.5,
          "vn_err": 1.2,
          "name": "BAYI"
        },
        {
          "lon": 92.438,
          "lat": 27.272,
          "ve": 12.5,
          "vn": 22.8,
          "ve_err": 0.7,
          "vn_err": 0.6,
          "name": "BOMD"
        },
        {
          "lon": 92.415,
          "lat": 27.27,
          "ve": 12.1,
          "vn": 24,
          "ve_err": 0.2,
          "vn_err": 0.3,
          "name": "BOMP"
        },
        {
          "lon": 94.387,
          "lat": 29.622,
          "ve": 18.3,
          "vn": 6.1,
          "ve_err": 0.4,
          "vn_err": 0.3,
          "name": "BT14"
        },
        {
          "lon": 97.456,
          "lat": 28.65,
          "ve": 12.8,
          "vn": -6.8,
          "ve_err": 1.1,
          "vn_err": 0.8,
          "name": "CHY1"
        },
        {
          "lon": 93.339,
          "lat": 29.9,
          "ve": 19.2,
          "vn": 9.1,
          "ve_err": 1,
          "vn_err": 0.8,
          "name": "GBD1"
        },
        {
          "lon": 93.242,
          "lat": 29.883,
          "ve": 19.3,
          "vn": 10.6,
          "ve_err": 0.4,
          "vn_err": 0.4,
          "name": "GONG"
        },
        {
          "lon": 97.217,
          "lat": 29.153,
          "ve": 13,
          "vn": -5,
          "ve_err": 1,
          "vn_err": 0.8,
          "name": "GYX1"
        },
        {
          "lon": 92.439,
          "lat": 28.432,
          "ve": 14.3,
          "vn": 15.6,
          "ve_err": 2.1,
          "vn_err": 1.9,
          "name": "LOZ1"
        },
        {
          "lon": 93.082,
          "lat": 29.082,
          "ve": 17.7,
          "vn": 12.5,
          "ve_err": 1.1,
          "vn_err": 0.9,
          "name": "LAC1"
        },
        {
          "lon": 94.36,
          "lat": 29.648,
          "ve": 19.2,
          "vn": 7.4,
          "ve_err": 0.4,
          "vn_err": 0.3,
          "name": "LINZ"
        },
        {
          "lon": 94.724,
          "lat": 29.737,
          "ve": 18.7,
          "vn": 5,
          "ve_err": 1,
          "vn_err": 0.8,
          "name": "LLZ1"
        },
        {
          "lon": 92.46,
          "lat": 28.414,
          "ve": 16.4,
          "vn": 16.7,
          "ve_err": 0.4,
          "vn_err": 0.3,
          "name": "LNGZ"
        },
        {
          "lon": 94.418,
          "lat": 29.601,
          "ve": 18.6,
          "vn": 5.9,
          "ve_err": 0.9,
          "vn_err": 0.8,
          "name": "LZX1"
        },
        {
          "lon": 94.184,
          "lat": 29.189,
          "ve": 17.4,
          "vn": 7.8,
          "ve_err": 1,
          "vn_err": 0.8,
          "name": "MLX1"
        },
        {
          "lon": 94.892,
          "lat": 29.541,
          "ve": 17,
          "vn": 3.5,
          "ve_err": 1,
          "vn_err": 0.8,
          "name": "PQX1"
        },
        {
          "lon": 97.016,
          "lat": 28.131,
          "ve": 12,
          "vn": 6.7,
          "ve_err": 0.5,
          "vn_err": 0.5,
          "name": "WALG"
        },
        {
          "lon": 92.576,
          "lat": 28.432,
          "ve": 16.5,
          "vn": 15.7,
          "ve_err": 0.3,
          "vn_err": 0.3,
          "name": "Y265"
        },
        {
          "lon": 99.14,
          "lat": 27.311,
          "ve": 4.5,
          "vn": -10.1,
          "ve_err": 0.5,
          "vn_err": 0.5,
          "name": "Y293"
        },
        {
          "lon": 98.625,
          "lat": 26.018,
          "ve": -2.9,
          "vn": -6.6,
          "ve_err": 0.6,
          "vn_err": 0.6,
          "name": "YD07"
        },
        {
          "lon": 98.78,
          "lat": 25.947,
          "ve": -3.3,
          "vn": -8.3,
          "ve_err": 0.7,
          "vn_err": 0.7,
          "name": "YD08"
        },
        {
          "lon": 98.94,
          "lat": 25.836,
          "ve": -2.9,
          "vn": -8.2,
          "ve_err": 0.7,
          "vn_err": 0.6,
          "name": "YD11"
        },
        {
          "lon": 95.901,
          "lat": 28.778,
          "ve": 17.4,
          "vn": 13.9,
          "ve_err": 0.7,
          "vn_err": 0.8,
          "name": "AMOL"
        },
        {
          "lon": 95.902,
          "lat": 28.801,
          "ve": 15.3,
          "vn": 14.4,
          "ve_err": 0.3,
          "vn_err": 0.3,
          "name": "ANIN"
        },
        {
          "lon": 95.966,
          "lat": 28.325,
          "ve": 16.1,
          "vn": 17.9,
          "ve_err": 0.4,
          "vn_err": 0.3,
          "name": "HUNL"
        },
        {
          "lon": 96.359,
          "lat": 27.756,
          "ve": 11.3,
          "vn": 18.7,
          "ve_err": 0.6,
          "vn_err": 0.6,
          "name": "KNGR"
        },
        {
          "lon": 95.855,
          "lat": 28.449,
          "ve": 13.5,
          "vn": 17.4,
          "ve_err": 0.7,
          "vn_err": 0.7,
          "name": "RALI"
        },
        {
          "lon": 96.396,
          "lat": 27.973,
          "ve": 12.8,
          "vn": 17.3,
          "ve_err": 0.3,
          "vn_err": 0.3,
          "name": "TDNG"
        },
        {
          "lon": 95.834,
          "lat": 28.224,
          "ve": 15.6,
          "vn": 19.9,
          "ve_err": 0.7,
          "vn_err": 0.8,
          "name": "TWGN"
        },
        {
          "lon": 96.469,
          "lat": 28.059,
          "ve": 11,
          "vn": 20.4,
          "ve_err": 3,
          "vn_err": 3.6,
          "name": "AMLG"
        },
        {
          "lon": 95.829,
          "lat": 28.491,
          "ve": 12.7,
          "vn": 18,
          "ve_err": 2.1,
          "vn_err": 2.8,
          "name": "ARZO"
        },
        {
          "lon": 95.847,
          "lat": 28.091,
          "ve": 11.5,
          "vn": 24.1,
          "ve_err": 1.8,
          "vn_err": 2.7,
          "name": "BALK"
        },
        {
          "lon": 95.665,
          "lat": 28.159,
          "ve": 17.5,
          "vn": 23.5,
          "ve_err": 1.9,
          "vn_err": 2.7,
          "name": "BMJR"
        },
        {
          "lon": 95.766,
          "lat": 27.912,
          "ve": 15.3,
          "vn": 21.7,
          "ve_err": 1.3,
          "vn_err": 2.4,
          "name": "CPKW"
        },
        {
          "lon": 96.292,
          "lat": 27.899,
          "ve": 15.2,
          "vn": 15,
          "ve_err": 2.6,
          "vn_err": 3.2,
          "name": "DEMW"
        },
        {
          "lon": 95.616,
          "lat": 28.27,
          "ve": 17.4,
          "vn": 20.4,
          "ve_err": 1.7,
          "vn_err": 2.6,
          "name": "DMBK"
        },
        {
          "lon": 96.543,
          "lat": 28.076,
          "ve": 12.9,
          "vn": 17.2,
          "ve_err": 2,
          "vn_err": 2.8,
          "name": "HLNG"
        },
        {
          "lon": 95.819,
          "lat": 28.178,
          "ve": 16.5,
          "vn": 20,
          "ve_err": 2.1,
          "vn_err": 2.8,
          "name": "KBLI"
        },
        {
          "lon": 95.913,
          "lat": 28.28,
          "ve": 14.6,
          "vn": 20.3,
          "ve_err": 1.6,
          "vn_err": 2.5,
          "name": "MY65"
        },
        {
          "lon": 95.909,
          "lat": 28.233,
          "ve": 12.7,
          "vn": 16.5,
          "ve_err": 2.9,
          "vn_err": 3.4,
          "name": "MYDA"
        },
        {
          "lon": 96.417,
          "lat": 27.992,
          "ve": 11.1,
          "vn": 18.2,
          "ve_err": 1.9,
          "vn_err": 2.8,
          "name": "PAYA"
        },
        {
          "lon": 95.745,
          "lat": 28.316,
          "ve": 18.1,
          "vn": 21.3,
          "ve_err": 2.1,
          "vn_err": 2.8,
          "name": "PTCM"
        },
        {
          "lon": 95.845,
          "lat": 28.147,
          "ve": 13.2,
          "vn": 20.7,
          "ve_err": 2.3,
          "vn_err": 3.1,
          "name": "RON1"
        },
        {
          "lon": 96.332,
          "lat": 27.913,
          "ve": 11.2,
          "vn": 19.8,
          "ve_err": 2.1,
          "vn_err": 2.8,
          "name": "THGM"
        },
        {
          "lon": 98.907,
          "lat": 28.488,
          "ve": 10.7,
          "vn": -9.3,
          "ve_err": 0.4,
          "vn_err": 0.4,
          "name": "DEQN"
        },
        {
          "lon": 93.968,
          "lat": 27.313,
          "ve": 12.5,
          "vn": 29,
          "ve_err": 2,
          "vn_err": 2.8,
          "name": "KIMN"
        },
        {
          "lon": 93.841,
          "lat": 27.619,
          "ve": 14.2,
          "vn": 19.9,
          "ve_err": 1.7,
          "vn_err": 2.5,
          "name": "ZIRO"
        },
        {
          "lon": 97.4,
          "lat": 27.35,
          "ve": 7.1,
          "vn": -3.9,
          "ve_err": 1.2,
          "vn_err": 1.2,
          "name": "PUTA"
        },
        {
          "lon": 96.73,
          "lat": 26.332,
          "ve": 6.9,
          "vn": 12.7,
          "ve_err": 1.2,
          "vn_err": 1.2,
          "name": "TANA"
        },
        {
          "lon": 94.142,
          "lat": 27.235,
          "ve": 11.4,
          "vn": 26.9,
          "ve_err": 1.5,
          "vn_err": 2.4,
          "name": "NLKP"
        },
        {
          "lon": 94.629,
          "lat": 26.99,
          "ve": 9.6,
          "vn": 23.9,
          "ve_err": 1.7,
          "vn_err": 2.5,
          "name": "SIBS"
        },
        {
          "lon": 91.46,
          "lat": 26.86,
          "ve": 9.8,
          "vn": 33,
          "ve_err": 1.5,
          "vn_err": 2.3,
          "name": "DEOT"
        },
        {
          "lon": 91.52,
          "lat": 27.29,
          "ve": 9.6,
          "vn": 27.2,
          "ve_err": 1.2,
          "vn_err": 1.8,
          "name": "KANG"
        },
        {
          "lon": 91.54,
          "lat": 27,
          "ve": 10,
          "vn": 25.6,
          "ve_err": 3.2,
          "vn_err": 4,
          "name": "NARP"
        },
        {
          "lon": 91.53,
          "lat": 27.11,
          "ve": 10.3,
          "vn": 25.1,
          "ve_err": 2.8,
          "vn_err": 4.2,
          "name": "WAMR"
        },
        {
          "lon": 94.159,
          "lat": 26.739,
          "ve": 11.4,
          "vn": 24.3,
          "ve_err": 2.8,
          "vn_err": 2.7,
          "name": "JRHT"
        },
        {
          "lon": 93.4,
          "lat": 26.571,
          "ve": 12.7,
          "vn": 29.9,
          "ve_err": 1.6,
          "vn_err": 1.6,
          "name": "KHRA"
        },
        {
          "lon": 94.475,
          "lat": 26.22,
          "ve": 7.9,
          "vn": 25.4,
          "ve_err": 0.3,
          "vn_err": 0.3,
          "name": "LUMA"
        },
        {
          "lon": 92.78,
          "lat": 26.618,
          "ve": 11.4,
          "vn": 30.4,
          "ve_err": 0.2,
          "vn_err": 0.3,
          "name": "TZPR"
        }
      ]
    }
  ],
  "lines": [
    {
      "coordinates": [
        [
          98.26526536371892,
          31.323646757573623
        ],
        [
          95.62818471435985,
          29.734760416207717
        ],
        [
          95.232622616956,
          27.264724386186497
        ],
        [
          93.38666616240465,
          25.41485317012413
        ],
        [
          90.0903153507058,
          24.977686279613714
        ],
        [
          88.24435889615445,
          23.415305443830214
        ],
        [
          92.375785246817,
          21.01653914427587
        ],
        [
          96.9027736948834,
          20.441446768493645
        ],
        [
          98.74873014943476,
          22.28202638865621
        ],
        [
          97.25438444813126,
          24.339028973288087
        ],
        [
          97.07857907150733,
          25.29578162329034
        ]
      ]
    }
  ]
}